mcli/__init__.py
mcli/config.py
mcli/version.py
mcli/admin/__init__.py
mcli/admin/helpers.py
mcli/api/__init__.py
mcli/api/exceptions.py
mcli/api/typing_future.py
mcli/api/utils.py
mcli/api/cluster/__init__.py
mcli/api/cluster/api_get_clusters.py
mcli/api/engine/__init__.py
mcli/api/engine/engine.py
mcli/api/engine/retry.py
mcli/api/inference_deployments/__init__.py
mcli/api/inference_deployments/api_create_default_deployment.py
mcli/api/inference_deployments/api_create_inference_deployment.py
mcli/api/inference_deployments/api_delete_inference_deployments.py
mcli/api/inference_deployments/api_get_inference_deployment_logs.py
mcli/api/inference_deployments/api_get_inference_deployments.py
mcli/api/inference_deployments/api_ping.py
mcli/api/inference_deployments/api_predict_inference_deployment.py
mcli/api/inference_deployments/api_stop_inference_deployments.py
mcli/api/inference_deployments/api_update_inference_deployments.py
mcli/api/mint/__init__.py
mcli/api/mint/shell.py
mcli/api/mint/tty.py
mcli/api/model/__init__.py
mcli/api/model/cluster_details.py
mcli/api/model/inference_deployment.py
mcli/api/model/run.py
mcli/api/model/run_debug_info.py
mcli/api/model/run_event.py
mcli/api/model/user.py
mcli/api/organizations/__init__.py
mcli/api/organizations/api_get_organizations.py
mcli/api/runs/__init__.py
mcli/api/runs/api_create_interactive_run.py
mcli/api/runs/api_create_run.py
mcli/api/runs/api_create_run_event.py
mcli/api/runs/api_delete_runs.py
mcli/api/runs/api_get_run_debug_info.py
mcli/api/runs/api_get_run_logs.py
mcli/api/runs/api_get_runs.py
mcli/api/runs/api_start_run.py
mcli/api/runs/api_stop_runs.py
mcli/api/runs/api_update_run.py
mcli/api/runs/api_update_run_metadata.py
mcli/api/runs/api_watch_run.py
mcli/api/schema/__init__.py
mcli/api/schema/generic_model.py
mcli/api/secrets/__init__.py
mcli/api/secrets/api_create_secret.py
mcli/api/secrets/api_delete_secrets.py
mcli/api/secrets/api_get_secrets.py
mcli/api/users/__init__.py
mosaicml_cli-0.8.3.dist-info/METADATA
mosaicml_cli-0.8.3.dist-info/WHEEL
mosaicml_cli-0.8.3.dist-info/entry_points.txt
mosaicml_cli-0.8.3.dist-info/top_level.txt
mosaicml_cli-0.8.3.dist-info/RECORD
